pyahn/__init__.py
pyahn/core.py
pyahn/helpers.py
pyahn/model.py
pyahn-2.0.0.dist-info/LICENSE
pyahn-2.0.0.dist-info/METADATA
pyahn-2.0.0.dist-info/WHEEL
pyahn-2.0.0.dist-info/entry_points.txt
pyahn-2.0.0.dist-info/top_level.txt
pyahn-2.0.0.dist-info/RECORD
